sixties/__init__.py
sixties/__main__.py
sixties/cli.py
sixties-2023.10.22.dist-info/LICENSE
sixties-2023.10.22.dist-info/METADATA
sixties-2023.10.22.dist-info/WHEEL
sixties-2023.10.22.dist-info/entry_points.txt
sixties-2023.10.22.dist-info/top_level.txt
sixties-2023.10.22.dist-info/RECORD
