Metadata-Version: 2.1
Name: sixties
Version: 2023.10.22
Summary: Parsing of fixed width text databases derived in the Seventies from the Sixties' spirit of the previous century.
Author-email: Stefan Hagen <stefan@hagen.link>
Maintainer-email: Stefan Hagen <stefan@hagen.link>
Project-URL: Homepage, https://git.sr.ht/~sthagen/sixties
Project-URL: Bug-Tracker, https://todo.sr.ht/~sthagen/sixties
Project-URL: Documentation, https://codes.dilettant.life/docs/sixties
Project-URL: Source-Code, https://git.sr.ht/~sthagen/sixties
Project-URL: Test-Coverage, https://codes.dilettant.life/coverage/sixties
Keywords: developer-tools,validation,verification
Classifier: Development Status :: 3 - Alpha
Classifier: Intended Audience :: Developers
Classifier: License :: OSI Approved :: MIT License
Classifier: Programming Language :: Python :: 3.10
Classifier: Programming Language :: Python :: 3.11
Classifier: Programming Language :: Python :: 3.12
Classifier: Programming Language :: Python :: 3.9
Requires-Python: >=3.9
License-File: LICENSE
Requires-Dist: typer >=0.9.0
Provides-Extra: dev
Requires-Dist: black ; extra == 'dev'
Requires-Dist: coverage ; extra == 'dev'
Requires-Dist: hypothesis ; extra == 'dev'
Requires-Dist: mypy ; extra == 'dev'
Requires-Dist: pytest ; extra == 'dev'
Requires-Dist: pytest-cov ; extra == 'dev'
Requires-Dist: pytest-flake8 ; extra == 'dev'
Requires-Dist: ruff ; extra == 'dev'
